edx_username_changer/__init__.py
edx_username_changer/admin.py
edx_username_changer/apps.py
edx_username_changer/exceptions.py
edx_username_changer/signals.py
edx_username_changer/tasks.py
edx_username_changer/utils.py
edx_username_changer/settings/common.py
edx_username_changer/settings/devstack.py
edx_username_changer-0.4.0.dist-info/METADATA
edx_username_changer-0.4.0.dist-info/WHEEL
edx_username_changer-0.4.0.dist-info/entry_points.txt
edx_username_changer-0.4.0.dist-info/licenses/LICENCE.txt
edx_username_changer-0.4.0.dist-info/RECORD
