Metadata-Version: 2.4
Name: edx-username-changer
Version: 0.4.0
Summary: An edX plugin to change username of edx accounts through admin panel
Author: MIT Office of Digital Learning
License-Expression: BSD-3-Clause
License-File: LICENCE.txt
Keywords: Python,edx
Requires-Python: >=3.11
Requires-Dist: celery>=4.4.7
Requires-Dist: django>=4.0
Requires-Dist: djangorestframework>=3.14.0
Requires-Dist: edx-django-utils>4.0.0
